Workbook

Sheet README
B2: IQR SAMPLE - RAW DATA
B3: Every input and calculation behind the CircularEnergies CNG Fleet Conversion Impact Quantification Report
B5: Project | C5: CNG Fleet Conversion - Meridian Logistics Nigeria Ltd (fictional)
B6: Reporting period | C6: July 2025 - June 2026
B7: Scope | C7: 40 vehicles: 28 bi-fuel petrol conversions + 12 diesel dual-fuel retrofits
B8: Route | C8: Lagos - Ibadan - Abuja
B9: Report version | C9: August 2026 v1.0 - Final
B10: Prepared by | C10: CircularEnergies Ltd, Abuja
B11: Report type | C11: Sample / demonstration
B12: Purpose of this file | C12: Companion raw data to the published IQR - every figure in the report is traceable to a cell here
B14: WHAT IS IN THIS WORKBOOK
B15: Segments | C15: The two technical segments - bi-fuel and dual-fuel - with all vehicle-level parameters
B16: Emission Factors | C16: Every factor and constant used in the calculation, with source and standard
B17: Monthly Operations | C17: 12 months of reconciled operating data: distance, CNG, fuel displaced, tCO₂e, savings
B18: Emissions Calculation | C18: The full baseline → project → gross avoided → slip → net avoided chain
B19: Financial Summary | C19: Fuel cost avoided, CNG purchased, maintenance, cylinder reserve, net saving
B20: Sensitivity | C20: Net avoided emissions across a range of methane slip assumptions
B21: DFI Indicators | C21: Indicators populated for AfDB, IFC-CAFI, FCDO, PCNGi and Nigeria NDC frameworks
B22: Data Sources | C22: Where each input came from - telematics, dispensing records, fuel cards
B24: COLOUR CONVENTIONS
B25: Blue | C25: Input value or measured data
B26: Black | C26: Formula computed within the sheet
B27: Green | C27: Cross-sheet link
B28: Yellow fill | C28: Key parameter or headline result
B30: Meridian Logistics Nigeria Ltd is a fictional entity. All figures are simulated for demonstration purposes and must not be relied upon for investment, disclosure or compliance decisions. This workbook is released as a companion to the published sample IQR to demonstrate the calculation methodology, evidence chain and reporting structure CircularEnergies applies to impact quantification engagements.

Sheet Segments
A1: SEGMENT PARAMETERS
A2: The converted fleet comprises two technically distinct segments, each modelled separately.
A4: Parameter | B4: Unit | C4: Segment A — Bi-fuel | D4: Segment B — Dual-fuel | E4: Total / Note
A5: Vehicle class | C5: Light commercial vans and minibuses | D5: Rigid and articulated trucks
A6: Units converted | B6: vehicles | C6: 28 | D6: 12 | E6: =C6+D6 -> 40
A7: Baseline fuel | C7: Petrol (PMS) | D7: Diesel (AGO)
A8: Conversion technology | C8: Sequential bi-fuel CNG kit | D8: Diesel dual-fuel retrofit
A9: Mean daily distance | B9: km | C9: 165 | D9: 295
A10: Operating days per month | B10: days | C10: 26 | D10: 24
A11: Baseline fuel economy | B11: km / litre | C11: 8.5 | D11: 3.3
A12: Achieved substitution rate | B12: % | C12: 0.84 | D12: 0.55
A13: Annual distance | B13: km | C13: =C6*C9*C10*12 -> 1441440 | D13: =D6*D9*D10*12 -> 1019520 | E13: =C13+D13 -> 2460960
A14: Baseline liquid fuel | B14: litres | C14: =C13/C11 -> 169581.18 | D14: =D13/D11 -> 308945.45 | E14: =C14+D14 -> 478526.63
A15: Liquid fuel displaced | B15: litres | C15: =C14*C12 -> 142448.19 | D15: =D14*D12 -> 169920 | E15: =C15+D15 -> 312368.19
A16: Residual liquid fuel | B16: litres | C16: =C14-C15 -> 27132.988 | D16: =D14-D15 -> 139025.45 | E16: =C16+D16 -> 166158.44
A17: Conversion capex | B17: ₦ | C17: 23800000 | D17: 50400000 | E17: =C17+D17 -> 74200000
A18: Capex per vehicle | B18: ₦ | C18: =C17/C6 -> 850000 | D18: =D17/D6 -> 4200000

Sheet Emission Factors
A1: EMISSION FACTORS AND CONSTANTS
A2: Every factor and standard applied in the report.
A4: Component | B4: Source / standard | C4: Value applied | D4: Unit
A5: Petrol emission factor | B5: IPCC 2006 Guidelines, Vol. 2 Ch. 3, Tier 1 | C5: 2.31 | D5: kgCO₂ / L
A6: Diesel emission factor | B6: IPCC 2006 Guidelines, Vol. 2 Ch. 3, Tier 1 | C6: 2.68 | D6: kgCO₂ / L
A7: CNG emission factor | B7: IPCC 2006 Guidelines, natural gas | C7: 2.75 | D7: kgCO₂ / kg
A8: CNG density | B8: Nigerian pipeline gas specification | C8: 0.68 | D8: kg / SCM
A9: Petrol energy equivalence | B9: Lower heating value ratio | C9: 1 kg CNG ≡ 1.50 L petrol | D9: kg → L
A10: Diesel energy equivalence | B10: Lower heating value ratio | C10: 1 kg CNG ≡ 1.30 L diesel | D10: kg → L
A11: Methane fraction in CNG | B11: Gas supplier composition certificate | C11: 0.9 | D11: by mass
A12: Methane slip rate | B12: Conservative retrofit assumption | C12: 0.015 | D12: of throughput
A13: Methane GWP (100-yr) | B13: IPCC AR5 | C13: 28 | D13: × CO₂
A14: Reporting protocol | B14: GHG Protocol Corporate Standard | C14: Scope 1 – mobile combustion
A15: Applicable methodology | B15: CDM AMS-III.S (Gold Standard, Article 6.4 transitionable) | C15: Low-emission vehicles and technologies to commercial vehicle fleets

Sheet Monthly Operations
A1: MONTHLY OPERATING DATA
A2: Twelve months of reconciled operating data. Seasonal variation reflects rainy-season haulage and Q4 volume.
A4: Month | B4: Distance (km) | C4: CNG (SCM) | D4: Petrol displaced (L) | E4: Diesel displaced (L) | F4: tCO₂e avoided | G4: Net saving (₦) | H4: Flag
A5: Jul 2025 | B5: 201799 | C5: 27214 | D5: 11681 | E5: 13933 | F5: 6.44 | G5: 22058075 | H5: M1
A6: Aug 2025 | B6: 194416 | C6: 26218 | D6: 11253 | E6: 13424 | F6: 6.2 | G6: 21251072 | H6: M1
A7: Sep 2025 | B7: 211643 | C7: 28541 | D7: 12251 | E7: 14613 | F7: 6.75 | G7: 23134079 | H7: M1
A8: Oct 2025 | B8: 206721 | C8: 27877 | D8: 11966 | E8: 14273 | F8: 6.6 | G8: 22596077 | H8: M1
A9: Nov 2025 | B9: 214104 | C9: 28873 | D9: 12393 | E9: 14783 | F9: 6.83 | G9: 23403079 | H9: M1
A10: Dec 2025 | B10: 194416 | C10: 26218 | D10: 11253 | E10: 13424 | F10: 6.2 | G10: 21251072 | H10: M1
A11: Jan 2026 | B11: 184572 | C11: 24890 | D11: 10684 | E11: 12744 | F11: 5.89 | G11: 20175068 | H11: M1
A12: Feb 2026 | B12: 189494 | C12: 25554 | D12: 10969 | E12: 13084 | F12: 6.05 | G12: 20713070 | H12: M1
A13: Mar 2026 | B13: 206721 | C13: 27877 | D13: 11966 | E13: 14273 | F13: 6.6 | G13: 22596077 | H13: M1
A14: Apr 2026 | B14: 216564 | C14: 29205 | D14: 12535 | E14: 14953 | F14: 6.91 | G14: 23672080 | H14: M1
A15: May 2026 | B15: 226408 | C15: 30532 | D15: 13105 | E15: 15633 | F15: 7.23 | G15: 24748084 | H15: M1
A16: Jun 2026 | B16: 214104 | C16: 28873 | D16: 12393 | E16: 14783 | F16: 6.83 | G16: 23403079 | H16: M1
A17: TOTAL - 12 months | B17: =SUM(B5:B16) -> 2460962 | C17: =SUM(C5:C16) -> 331872 | D17: =SUM(D5:D16) -> 142449 | E17: =SUM(E5:E16) -> 169920 | F17: =SUM(F5:F16) -> 78.53 | G17: =SUM(G5:G16) -> 269000912
A19: Notes
A20: Flag M1 (data quality - measurement note): dispensing station receipts reconciled to fleet card statements. Where a station's paper record and the card statement disagreed by more than 2% in the month, both records are retained in the raw operating log and the reconciled figure applied here uses the fleet card number as primary unless the dispatch record supports the station figure. This affected M1 (Jul 2025) through M6 (Dec 2025); the programme moved to fully digital dispensing from Jan 2026 and the flag no longer applies from that month.

Sheet Emissions Calculation
A1: EMISSIONS CALCULATION CHAIN
A2: Baseline → project → gross avoided → methane slip → net avoided. Every step referenced to source data.
A4: Step | B4: Source cells | C4: Calculation shown in report | D4: Result | E4: Unit
A5: Baseline — petrol | B5: 'Monthly Operations'!D17 × 'Emission Factors'!C5 | C5: 142,448 L × 2.31 kgCO₂/L | D5: ='Monthly Operations'!$D$17*'Emission Factors'!$C$5/1000 -> 329.05719 | E5: tCO₂
A6: Baseline — diesel | B6: 'Monthly Operations'!E17 × 'Emission Factors'!C6 | C6: 169,920 L × 2.68 kgCO₂/L | D6: ='Monthly Operations'!$E$17*'Emission Factors'!$C$6/1000 -> 455.3856 | E6: tCO₂
A7: Total baseline emissions | B7: Sum of the two | C7: Displaced fuel, counterfactual case | D7: =D5+D6 -> 784.44279 | E7: tCO₂
A8: CNG throughput — kg | B8: 'Monthly Operations'!C17 × 'Emission Factors'!C8 | C8: 331,872 SCM × 0.68 kg/SCM | D8: ='Monthly Operations'!$C$17*'Emission Factors'!$C$8 -> 225672.96 | E8: kg
A9: Project — CNG combustion | B9: D8 × 'Emission Factors'!C7 | C9: 225,673 kg × 2.75 kgCO₂/kg | D9: =D8*'Emission Factors'!$C$7/1000 -> 620.60064 | E9: tCO₂
A10: Gross avoided — tank-to-wheel | B10: Baseline − Project | C10: 784.44 − 620.60 | D10: =D7-D9 -> 163.84215 | E10: tCO₂
A11: Methane throughput | B11: D8 × 'Emission Factors'!C11 | C11: 225,673 kg × 90% CH₄ | D11: =D8*'Emission Factors'!$C$11 -> 203105.66 | E11: kg
A12: Methane slipped | B12: D11 × 'Emission Factors'!C12 | C12: 203,106 kg × 1.5% | D12: =D11*'Emission Factors'!$C$12 -> 3046.585 | E12: kg CH₄
A13: Slip in CO₂-equivalent | B13: D12 × 'Emission Factors'!C13 | C13: 3,047 kg × GWP 28 | D13: =D12*'Emission Factors'!$C$13/1000 -> 85.304379 | E13: tCO₂e
A14: NET AVOIDED EMISSIONS | B14: Gross − Slip | C14: 163.84 − 85.30 | D14: =D10-D13 -> 78.537771 | E14: tCO₂e
A17: RECONCILIATION TO MONTHLY OPERATIONS
A18: Sum of monthly tCO₂e avoided | D18: ='Monthly Operations'!F17 -> 78.53
A19: Net avoided (calculated above) | D19: =D14 -> 78.537771
A20: Difference (rounding) | D20: =D18-D19 -> -0.00777112
A22: CARBON INTENSITY (VEHICLE-KM BASIS)
A23: Baseline - liquid fuel only | D23: =D7*1000/'Monthly Operations'!$B$17 -> 0.31875453 | E23: kgCO₂e / km
A24: Post-conversion - net of methane slip | D24: =(D9+D13)*1000/'Monthly Operations'!$B$17 -> 0.28684109 | E24: kgCO₂e / km
A25: Fleet-wide intensity reduction | D25: =1-D24/D23 -> 0.10011918

Sheet Financial Summary
A1: FINANCIAL SUMMARY
A2: Twelve-month fuel cost avoided, less CNG purchased and incremental costs. All figures in naira.
A4: Line | B4: Basis | C4: Calculation shown in report | D4: Amount (₦)
A5: Petrol cost avoided | B5: Petrol displaced × price | C5: 142,448 L × ₦1,050/L | D5: ='Monthly Operations'!$D$17*$D$17 -> 149571450
A6: Diesel cost avoided | B6: Diesel displaced × price | C6: 169,920 L × ₦1,350/L | D6: ='Monthly Operations'!$E$17*$D$18 -> 229392000
A7: Gross fuel cost avoided | B7: Sum of the two | C7: Baseline liquid fuel spend | D7: =D5+D6 -> 378963450
A8: Less: CNG purchased | B8: CNG volume × price | C8: 331,872 SCM × ₦300/SCM | D8: =-'Monthly Operations'!$C$17*$D$19 -> -99561600
A9: Less: incremental maintenance | B9: Per vehicle × fleet | C9: ₦180,000 × 40 vehicles | D9: =-$D$20*(Segments!$C$6+Segments!$D$6) -> -7200000
A10: Less: cylinder recertification reserve | B10: Accrual toward 3-year test cycle | C10: Programme provision | D10: =-$D$21 -> -3200000
A11: NET FUEL COST SAVING | B11: 71.0% of baseline spend | C11: Reported outcome | D11: =D5+D6+D8+D9+D10 -> 269001850
A17: Petrol price applied | D17: 1050
A18: Diesel price applied | D18: 1350
A19: CNG price applied | D19: 300
A20: Incremental maintenance per vehicle | D20: 180000
A21: Cylinder recertification reserve | D21: 3200000
A24: RECONCILIATION AND KEY RATIOS
A25: Sum of monthly net saving | D25: ='Monthly Operations'!G17 -> 269000912
A26: Net saving (calculated above) | D26: =D11 -> 269001850
A27: Difference (rounding) | D27: =D25-D26 -> -938
A29: Net saving as % of baseline fuel spend | D29: =D11/D7 -> 0.70983587
A30: Programme conversion capex (from Segments) | D30: =Segments!$E$17 -> 74200000
A31: Payback period on net saving | D31: =D30/D11*12 -> 3.3100144 | E31: months
A34: CARBON MARKET VALUE (INDICATIVE)
A35: Voluntary carbon market price | D35: 8.5 | E35: US$ / tCO₂e
A36: USD / NGN exchange rate | D36: 1580 | E36: ₦ / US$
A37: Net avoided emissions | D37: ='Emissions Calculation'!D14 -> 78.537771 | E37: tCO₂e
A38: Gross indicative carbon value | D38: =D37*D35*D36 -> 1054762.3
A39: As % of fuel cost saving | D39: =D38/D11 -> 0.0039210224

Sheet Sensitivity
A1: SENSITIVITY - NET AVOIDED EMISSIONS
A2: Net avoided emissions across a range of methane slip assumptions. The 1.5% base case is the number reported.
A4: Methane slip assumption | B4: Description | C4: Net avoided (tCO₂e) | D4: Variance vs base case
A5: 0.005 | B5: Best-in-class calibration | C5: 135.4 | D5: 0.72
A6: 0.01 | B6: Well-maintained retrofit | C6: 106.97 | D6: 0.36
A7: 0.015 | B7: Base case applied | C7: 78.54 | D7: 0
A8: 0.025 | B8: Poorly maintained fleet | C8: 21.67 | D8: -0.72
A9: 0.03 | B9: Upper literature bound | C9: -6.77 | D9: -1.09
A12: Methane slip is the single highest-value refinement available to this programme. Direct exhaust measurement on a sample of vehicles would materially tighten this estimate. The upper literature bound of 3.0% turns the programme net-negative on avoided emissions even though it remains highly cash-positive. This asymmetry is why measured slip data — rather than a literature value — is worth commissioning before any carbon monetisation strategy is set.

Sheet DFI Indicators
A1: DFI RESULTS FRAMEWORK - POPULATED INDICATORS
A2: Indicators populated in the format required by the principal DFIs active in Nigerian transport lending.
A4: Institution | B4: Indicator | C4: Reported value | D4: Unit
A5: African Development Bank | B5: Greenhouse gas emissions reduced | C5: 78.54 | D5: tCO₂e / yr
A6: African Development Bank | B6: Private sector capital mobilised | C6: 46962 | D6: US$
A7: IFC – CAFI | B7: Annual GHG emissions avoided | C7: 78.54 | D7: tCO₂e
A8: IFC – CAFI | B8: Climate finance eligible investment | C8: 46962 | D8: US$
A9: FCDO | B9: Number of assets converted to lower-carbon fuel | C9: 40 | D9: vehicles
A10: FCDO | B10: Annual fuel cost saving to beneficiary | C10: 170254 | D10: US$
A11: Nigeria – PCNGi | B11: Vehicles converted under programme | C11: 40 | D11: vehicles
A12: Nigeria – PCNGi | B12: Litres of imported liquid fuel displaced | C12: 312368 | D12: litres
A13: Nigeria NDC | B13: Transport sector mitigation contribution | C13: 78.54 | D13: tCO₂e
A15: Every indicator above is derived from the same underlying data set on Monthly Operations and Emissions Calculation. The USD-denominated figures are converted at ₦1,580/US$ — the period-average exchange rate applied on Financial Summary. Where an institution's template requires additional breakdown by sub-project, vehicle class or reporting period, the raw data supports it without recalculation.

Sheet Data Sources
A1: DATA SOURCES AND QUALITY CONTROLS
A2: Where each raw input came from and the reconciliation applied.
A4: Data category | B4: Primary source | C4: Reconciliation basis | D4: Variance tolerance
A5: Distance | B5: Vehicle telematics, monthly aggregation | C5: Cross-checked against dispatch records; per-vehicle exception review over ±2% | D5: ±2%
A6: CNG purchased | B6: Station dispensing receipts | C6: Reconciled to fleet card statements, vehicle by vehicle, monthly | D6: ±1.5%
A7: Liquid fuel purchased | B7: Fuel card transaction data | C7: Matched to vehicle registration; anomalies flagged for driver review | D7: ±1%
A8: Fuel displacement | B8: Derived from measured CNG consumption | C8: Applied energy equivalence then validated against 12-month pre-conversion baseline decline in liquid fuel purchases | D8: ±5%
A9: Emission factors | B9: IPCC 2006 Guidelines, Vol. 2, Ch. 3, Tier 1 | C9: Published values; no in-house adjustment | D9: n/a
A10: Methane slip | B10: Conservative literature retrofit assumption | C10: Applied uniformly at 1.5%; sensitised across 0.5%–3.0% range | D10: See Sensitivity tab
A11: Fuel prices | B11: NNPCL retail postings and station receipts | C11: Period-average prices applied; monthly variation available on request | D11: n/a
A12: Exchange rate | B12: CBN period-average window rate | C12: Applied uniformly to all USD-denominated indicators | D12: n/a
A15: This report has been prepared by CircularEnergies as an independent third party using data supplied by the client. It has NOT been subjected to external limited or reasonable assurance under ISAE 3410. Where a lender or investor requires assured figures, this data structure is designed to support an assurance engagement without restructuring — each cell traces back to a primary source named on this tab.
